README.rst
setup.py
Flask_Binding.egg-info/PKG-INFO
Flask_Binding.egg-info/SOURCES.txt
Flask_Binding.egg-info/dependency_links.txt
Flask_Binding.egg-info/requires.txt
Flask_Binding.egg-info/top_level.txt
flask_binding/__init__.py
flask_binding/binder.py
flask_binding/binders.py
flask_binding/errors.py
flask_binding/sources.py