Metadata-Version: 1.1
Name: Flask-Binding
Version: 0.6.2
Summary: Adds support to turn arguments from the Flask request into method parameters.
Home-page: https://github.com/viniciuschiele/flask-binding
Author: Vinicius Chiele
Author-email: vinicius.chiele@gmail.com
License: Apache 2.0
Keywords: flask,rest,parse,request
Platform: UNKNOWN
Classifier: Development Status :: 5 - Production/Stable
Classifier: Intended Audience :: Developers
Classifier: Natural Language :: English
Classifier: Operating System :: OS Independent
Classifier: Programming Language :: Python
Classifier: Programming Language :: Python :: 3
Classifier: Programming Language :: Python :: 3.2
Classifier: Programming Language :: Python :: 3.3
Classifier: Programming Language :: Python :: 3.4
Classifier: Programming Language :: Python :: Implementation :: CPython
